hwpwn/__init__.py
hwpwn/common.py
hwpwn/data.py
hwpwn/flow.py
hwpwn/hwpwn.py
hwpwn/plot.py
hwpwn-0.1.2.dist-info/LICENSE
hwpwn-0.1.2.dist-info/METADATA
hwpwn-0.1.2.dist-info/WHEEL
hwpwn-0.1.2.dist-info/entry_points.txt
hwpwn-0.1.2.dist-info/RECORD
