Metadata-Version: 2.1
Name: hwpwn
Version: 0.1.2
Summary: Hardware security testing tool
License: MIT
Author: jemos
Author-email: contact@jemos.net
Requires-Python: >=3.9,<3.12
Classifier: License :: OSI Approved :: MIT License
Classifier: Programming Language :: Python :: 3
Classifier: Programming Language :: Python :: 3.9
Classifier: Programming Language :: Python :: 3.10
Classifier: Programming Language :: Python :: 3.11
Requires-Dist: PyWavelets (>=1.4.0,<2.0.0)
Requires-Dist: colorama (>=0.4.6,<0.5.0)
Requires-Dist: furo (>=2023.3.27,<2024.0.0)
Requires-Dist: matplotlib (>=3.7.1,<4.0.0)
Requires-Dist: pandas (>=2.0.0,<3.0.0)
Requires-Dist: python-dateutil (>=2.8.2,<3.0.0)
Requires-Dist: ruamel.yaml (>=0.16.12)
Requires-Dist: scipy (>=1.10.1,<2.0.0)
Requires-Dist: typer[all] (>=0.7.0,<0.8.0)
